pgos_cli/__init__.py
pgos_cli/pgos_asset_uploader.py
pgos_cli/pgos_backend_apis.py
pgos_cli/pgos_cli_client.py
pgos_cli/pgos_cli_config.py
pgos_cli/pgos_cmd_center.py
pgos_cli/pgos_cmdline.py
pgos_cli/pgos_tools.py
pgos_cli/pgos_uploader_impl_cos.py
pgos_cli/pgos_uploader_impl_s3.py
pgos_cli/win32_unicode_argv.py
pgos_cli_python_sdk_v1-0.2.16.168.dist-info/licenses/LICENSE
pgos_cli_python_sdk_v1-0.2.16.168.dist-info/METADATA
pgos_cli_python_sdk_v1-0.2.16.168.dist-info/WHEEL
pgos_cli_python_sdk_v1-0.2.16.168.dist-info/top_level.txt
pgos_cli_python_sdk_v1-0.2.16.168.dist-info/RECORD
