Metadata-Version: 2.4
Name: pgos-cli-python-sdk-v1
Version: 0.2.16.168
Summary: PGOS commandline interface
Author-email: yilungao <yilungao@tencent.com>
Project-URL: Homepage, https://pgos.intlgame.com/
Classifier: Programming Language :: Python :: 3
Classifier: License :: OSI Approved :: MIT License
Classifier: Operating System :: OS Independent
Requires-Python: >=3.8
License-File: LICENSE
Requires-Dist: boto3
Requires-Dist: cos-python-sdk-v5
Dynamic: license-file
